django_quotes/__init__.py
django_quotes/admin.py
django_quotes/apps.py
django_quotes/models.py
django_quotes/py.typed
django_quotes/receivers.py
django_quotes/rules.py
django_quotes/signals.py
django_quotes/tasks.py
django_quotes/urls.py
django_quotes/utils.py
django_quotes/views.py
django_quotes/api/__init__.py
django_quotes/api/serializers.py
django_quotes/api/views.py
django_quotes/management/__init__.py
django_quotes/management/commands/__init__.py
django_quotes/management/commands/makemarkov.py
django_quotes/migrations/0001_squashed_0005_alter_groupmarkovmodel_created_and_more.py
django_quotes/migrations/0003_alter_source_slug_alter_sourcegroup_slug.py
django_quotes/migrations/0004_quote_pub_date.py
django_quotes/migrations/0005_alter_groupmarkovmodel_created_and_more.py
django_quotes/migrations/0006_alter_source_description_rendered.py
django_quotes/migrations/0007_source_text_model_sourcegroup_text_model.py
django_quotes/migrations/0008_auto_20240404_1952.py
django_quotes/migrations/0009_alter_source_text_model_alter_sourcegroup_text_model.py
django_quotes/migrations/0009_alter_source_text_model_alter_sourcegroup_text_model_squashed_0012_remove_sourcemarkovmodel_source_and_more.py
django_quotes/migrations/0010_alter_source_text_model_alter_sourcegroup_text_model.py
django_quotes/migrations/0011_alter_source_text_model_alter_sourcegroup_text_model.py
django_quotes/migrations/0012_remove_sourcemarkovmodel_source_and_more.py
django_quotes/migrations/0013_remove_quote_quote_rendered_and_more.py
django_quotes/migrations/0014_alter_source_text_model_alter_sourcegroup_text_model.py
django_quotes/migrations/__init__.py
django_quotes/static/.gitkeep
django_quotes/templates/base.html
django_quotes/templates/quotes/base.html
django_quotes/templates/quotes/group_create.html
django_quotes/templates/quotes/group_delete.html
django_quotes/templates/quotes/group_detail.html
django_quotes/templates/quotes/group_list.html
django_quotes/templates/quotes/group_update.html
django_quotes-0.6.1.dist-info/METADATA
django_quotes-0.6.1.dist-info/WHEEL
django_quotes-0.6.1.dist-info/licenses/LICENSE
django_quotes-0.6.1.dist-info/RECORD
