Metadata-Version: 2.4
Name: django-quotes
Version: 0.6.1
Summary: A reusable Django app to collect quotes for use in random retrieval or generation of sentences using Markov Chains.
Project-URL: Repository, https://codeberg.org/andrlik/django-quotes
Project-URL: Homepage, https://codeberg.org/andrlik/django-quotes
Project-URL: Documentation, https://django-quotes-app.readthedocs.io/en/latest/
Author-email: Daniel Andrlik <daniel@andrlik.org>
License-Expression: BSD-3-Clause
License-File: LICENSE
Classifier: Development Status :: 4 - Beta
Classifier: Framework :: Django
Classifier: Framework :: Django :: 5.1
Classifier: Framework :: Django :: 5.2
Classifier: License :: OSI Approved :: BSD License
Classifier: Programming Language :: Python :: 3.12
Classifier: Programming Language :: Python :: 3.13
Requires-Python: >=3.12
Requires-Dist: coreapi>=2.3.3
Requires-Dist: coreschema>=0.0.4
Requires-Dist: crispy-bootstrap4>=2024.1
Requires-Dist: django-cors-headers>=3.11.0
Requires-Dist: django-crispy-forms>=1.14.0
Requires-Dist: django-easy-logging>=0.70
Requires-Dist: django-markov>=0.4.1
Requires-Dist: djangorestframework>=3.13.1
Requires-Dist: docutils
Requires-Dist: drf-spectacular>=0.24.2
Requires-Dist: itypes>=1.2.0
Requires-Dist: loguru>=0.6.0
Requires-Dist: marisa-trie>=1.2.1
Requires-Dist: markdown>=3.3.6
Requires-Dist: numpy>=2.3.0
Requires-Dist: preshed>=3.0.10
Requires-Dist: python-slugify>=6.1.1
Requires-Dist: rules>=3.1
Requires-Dist: spacy>=3.8.7
Provides-Extra: test
Requires-Dist: argon2-cffi; extra == 'test'
Requires-Dist: django-coverage; extra == 'test'
Requires-Dist: django-coverage-plugin; extra == 'test'
Requires-Dist: django-environ; extra == 'test'
Requires-Dist: django-extensions; extra == 'test'
Requires-Dist: django-types; extra == 'test'
Requires-Dist: factory-boy>=3.3.0; extra == 'test'
Requires-Dist: faker; extra == 'test'
Requires-Dist: pytest-asyncio; extra == 'test'
Requires-Dist: pytest-cov; extra == 'test'
Requires-Dist: pytest-django; extra == 'test'
Requires-Dist: pytest-mock; extra == 'test'
Requires-Dist: pytest-sugar; extra == 'test'
